graph_generator_lib_py/__init__.py
graph_generator_lib_py/generator.py
graph_generator_lib_py-0.3.0.dist-info/DESCRIPTION.rst
graph_generator_lib_py-0.3.0.dist-info/METADATA
graph_generator_lib_py-0.3.0.dist-info/RECORD
graph_generator_lib_py-0.3.0.dist-info/WHEEL
graph_generator_lib_py-0.3.0.dist-info/metadata.json
graph_generator_lib_py-0.3.0.dist-info/top_level.txt
